<?xml version="1.0" encoding="utf-8"?><response status="ok" version="1.2" xsi:noNamespaceSchemaLocation="http://api.7digital.com/1.2/static/7digitalAPI.xsd" xmlns:xsd="http://www.w3.org/2001/XMLSchema" xmlns:xsi="http://www.w3.org/2001/XMLSchema-instance"><searchResults><page>1</page><pageSize>10</pageSize><totalItems>174</totalItems><searchResult><type>track</type><score>0.33278364</score><track id="11834914"><title>The Stranger (karaoke-version) As Made Famous By: Billy Joel</title><version /><artist id="258315"><name>Studio Group</name><appearsAs>Studio Group</appearsAs><url>http://xw.7digital.com/artist/studio-group/?partner=12192</url><image>http://artwork-cdn.7static.com/static/img/artistimages/00/002/583/0000258315_150.jpg</image><isPlaceholderImage>true</isPlaceholderImage></artist><trackNumber>11</trackNumber><duration>296</duration><explicitContent>false</explicitContent><isrc>USFB20621666</isrc><type>audio</type><release id="1078918"><title>Karaoke Singing The Songs Of Billy Joel</title><version /><type>Album</type><artist id="60565"><name>Karaoke</name><appearsAs>Karaoke</appearsAs><url>http://xw.7digital.com/artist/karaoke/?partner=12192</url><image>http://artwork-cdn.7static.com/static/img/artistimages/00/000/605/0000060565_150.jpg</image><isPlaceholderImage>true</isPlaceholderImage></artist><url>http://xw.7digital.com/artist/karaoke/release/karaoke-singing-the-songs-of-billy-joel/?partner=12192</url><image>http://artwork-cdn.7static.com/static/img/sleeveart/00/010/789/0001078918_50.jpg</image><releaseDate>2006-06-01T03:00:00Z</releaseDate><formats availableDrmFree="true"><format id="17"><fileFormat>MP3</fileFormat><bitRate>320</bitRate><drmFree>true</drmFree></format></formats><label id="21548"><name>Charly Records</name></label><licensor id="21"><name>Orchard</name></licensor><popularity>0</popularity></release><url>http://xw.7digital.com/artist/karaoke/release/karaoke-singing-the-songs-of-billy-joel/?partner=12192&amp;h=11</url><price><currency code="USD">$</currency><value xsi:nil="true" /><formattedPrice>N/A</formattedPrice><rrp xsi:nil="true" /><formattedRrp>N/A</formattedRrp><onSale>false</onSale></price><streamingReleaseDate>2006-06-01T00:00:00Z</streamingReleaseDate><discNumber>1</discNumber><popularity>0.1</popularity><number>11</number><download><releaseDate>2006-06-01T03:00:00Z</releaseDate><packages><package id="2"><description>Standard</description><price><currencyCode>USD</currencyCode><sevendigitalPrice xsi:nil="true" /><recommendedRetailPrice xsi:nil="true" /></price><formats><format id="17"><description>MP3 320</description></format></formats></package></packages></download></track></searchResult><searchResult><type>track</type><score>0.33278364</score><track id="37267846"><title>The Stranger (Originally Performed By Billy Joel)</title><version>Karaoke Version</version><artist id="1890195"><name>Hit Tunes Karaoke</name><appearsAs>Hit Tunes Karaoke</appearsAs><url>http://xw.7digital.com/artist/hit-tunes-karaoke/?partner=12192</url><image>http://artwork-cdn.7static.com/static/img/artistimages/00/018/901/0001890195_150.jpg</image><isPlaceholderImage>true</isPlaceholderImage></artist><trackNumber>30</trackNumber><duration>254</duration><explicitContent>false</explicitContent><isrc>CH6540868843</isrc><type>audio</type><release id="3544725"><title>Piano Man (Sing the Hits of Billy Joel)</title><version>Karaoke Version</version><type>Album</type><artist id="1890195"><name>Hit Tunes Karaoke</name><appearsAs>Hit Tunes Karaoke</appearsAs><url>http://xw.7digital.com/artist/hit-tunes-karaoke/?partner=12192</url><image>http://artwork-cdn.7static.com/static/img/artistimages/00/018/901/0001890195_150.jpg</image><isPlaceholderImage>true</isPlaceholderImage></artist><url>http://xw.7digital.com/artist/hit-tunes-karaoke/release/piano-man-sing-the-hits-of-billy-joel-karaoke-version/?partner=12192</url><image>http://artwork-cdn.7static.com/static/img/sleeveart/00/035/447/0003544725_50.jpg</image><releaseDate>2014-05-27T00:00:00Z</releaseDate><formats availableDrmFree="true"><format id="17"><fileFormat>MP3</fileFormat><bitRate>320</bitRate><drmFree>true</drmFree></format><format id="33"><fileFormat>M4A</fileFormat><bitRate>320</bitRate><drmFree>true</drmFree></format></formats><label id="14988"><name>iMusician Digital</name></label><licensor id="68"><name>Kontor</name></licensor><popularity>0</popularity></release><url>http://xw.7digital.com/artist/hit-tunes-karaoke/release/piano-man-sing-the-hits-of-billy-joel-karaoke-version/?partner=12192&amp;h=30</url><price><currency code="USD">$</currency><value>0.99</value><formattedPrice>$0.99</formattedPrice><rrp>0.99</rrp><formattedRrp>$0.99</formattedRrp><onSale>false</onSale></price><streamingReleaseDate>2014-05-27T00:00:00Z</streamingReleaseDate><discNumber>1</discNumber><popularity>0.1</popularity><number>30</number><download><releaseDate>2014-05-27T00:00:00Z</releaseDate><packages><package id="2"><description>Standard</description><price><currencyCode>USD</currencyCode><sevendigitalPrice>0.99</sevendigitalPrice><recommendedRetailPrice>0.99</recommendedRetailPrice></price><formats><format id="33"><description>AAC 320</description></format><format id="17"><description>MP3 320</description></format></formats></package></packages></download></track></searchResult><searchResult><type>track</type><score>0.32822496</score><track id="54624589"><title>The Stranger (Originally Performed by Billy Joel)</title><version>Karaoke Version</version><artist id="3223224"><name>Tom Arte</name><appearsAs>Tom Arte</appearsAs><url>http://xw.7digital.com/artist/tom-arte/?partner=12192</url><image>http://artwork-cdn.7static.com/static/img/artistimages/00/032/232/0003223224_150.jpg</image><isPlaceholderImage>true</isPlaceholderImage></artist><trackNumber>18</trackNumber><duration>290</duration><explicitContent>false</explicitContent><isrc>ESA011618421</isrc><type>audio</type><release id="5398670"><title>Best of Billy Joel</title><version /><type>Album</type><artist id="3223224"><name>Tom Arte</name><appearsAs>Tom Arte</appearsAs><url>http://xw.7digital.com/artist/tom-arte/?partner=12192</url><image>http://artwork-cdn.7static.com/static/img/artistimages/00/032/232/0003223224_150.jpg</image><isPlaceholderImage>true</isPlaceholderImage></artist><url>http://xw.7digital.com/artist/tom-arte/release/best-of-billy-joel-5398670/?partner=12192</url><image>http://artwork-cdn.7static.com/static/img/sleeveart/00/053/986/0005398670_50.jpg</image><releaseDate>2016-05-23T03:00:00Z</releaseDate><formats availableDrmFree="true"><format id="17"><fileFormat>MP3</fileFormat><bitRate>320</bitRate><drmFree>true</drmFree></format><format id="33"><fileFormat>M4A</fileFormat><bitRate>320</bitRate><drmFree>true</drmFree></format></formats><label id="566418"><name>Golden Backings</name></label><licensor id="126"><name>La Cupula</name></licensor><popularity>0</popularity></release><url>http://xw.7digital.com/artist/tom-arte/release/best-of-billy-joel-5398670/?partner=12192&amp;h=18</url><price><currency code="USD">$</currency><value>0.99</value><formattedPrice>$0.99</formattedPrice><rrp>0.99</rrp><formattedRrp>$0.99</formattedRrp><onSale>false</onSale></price><discNumber>1</discNumber><popularity>0.1</popularity><number>18</number><download><releaseDate>2016-05-23T03:00:00Z</releaseDate><packages><package id="2"><description>Standard</description><price><currencyCode>USD</currencyCode><sevendigitalPrice>0.99</sevendigitalPrice><recommendedRetailPrice>0.99</recommendedRetailPrice></price><formats><format id="33"><description>AAC 320</description></format><format id="17"><description>MP3 320</description></format></formats></package></packages></download></track></searchResult><searchResult><type>track</type><score>0.31910762</score><track id="13980652"><title>The Stranger (Originally By Billy Joel)</title><version /><artist id="989037"><name>Various Musique</name><appearsAs>Various Musique</appearsAs><url>http://xw.7digital.com/artist/various-musique/?partner=12192</url><image>http://artwork-cdn.7static.com/static/img/artistimages/00/009/890/0000989037_150.jpg</image><isPlaceholderImage>true</isPlaceholderImage></artist><trackNumber>14</trackNumber><duration>193</duration><explicitContent>false</explicitContent><isrc>USA371277866</isrc><type>audio</type><release id="1265340"><title>I Live For Rock Vol. 2</title><version /><type>Album</type><artist id="989037"><name>Various Musique</name><appearsAs>Various Musique</appearsAs><url>http://xw.7digital.com/artist/various-musique/?partner=12192</url><image>http://artwork-cdn.7static.com/static/img/artistimages/00/009/890/0000989037_150.jpg</image><isPlaceholderImage>true</isPlaceholderImage></artist><url>http://xw.7digital.com/artist/various-musique/release/i-live-for-rock-vol-2/?partner=12192</url><image>http://artwork-cdn.7static.com/static/img/sleeveart/00/012/653/0001265340_50.jpg</image><releaseDate>2011-05-24T03:00:00Z</releaseDate><formats availableDrmFree="true"><format id="17"><fileFormat>MP3</fileFormat><bitRate>320</bitRate><drmFree>true</drmFree></format></formats><label id="26252"><name>On-The-Go Music</name></label><licensor id="21"><name>Orchard</name></licensor><popularity>0</popularity></release><url>http://xw.7digital.com/artist/various-musique/release/i-live-for-rock-vol-2/?partner=12192&amp;h=14</url><price><currency code="USD">$</currency><value xsi:nil="true" /><formattedPrice>N/A</formattedPrice><rrp xsi:nil="true" /><formattedRrp>N/A</formattedRrp><onSale>false</onSale></price><streamingReleaseDate>2011-05-24T00:00:00Z</streamingReleaseDate><discNumber>1</discNumber><popularity>0.1</popularity><number>14</number><download><releaseDate>2011-05-24T03:00:00Z</releaseDate><packages><package id="2"><description>Standard</description><price><currencyCode>USD</currencyCode><sevendigitalPrice xsi:nil="true" /><recommendedRetailPrice xsi:nil="true" /></price><formats><format id="17"><description>MP3 320</description></format></formats></package></packages></download></track></searchResult><searchResult><type>track</type><score>0.31910762</score><track id="37824578"><title>The Stranger (Originally Performed By Billy Joel)</title><version>Karaoke Version</version><artist id="1890195"><name>Hit Tunes Karaoke</name><appearsAs>Hit Tunes Karaoke</appearsAs><url>http://xw.7digital.com/artist/hit-tunes-karaoke/?partner=12192</url><image>http://artwork-cdn.7static.com/static/img/artistimages/00/018/901/0001890195_150.jpg</image><isPlaceholderImage>true</isPlaceholderImage></artist><trackNumber>7</trackNumber><duration>254</duration><explicitContent>false</explicitContent><isrc>CH6540870719</isrc><type>audio</type><release id="3605857"><title>Karaoke Superhits, Vol. 432</title><version>Karaoke Version</version><type>Album</type><artist id="1890195"><name>Hit Tunes Karaoke</name><appearsAs>Hit Tunes Karaoke</appearsAs><url>http://xw.7digital.com/artist/hit-tunes-karaoke/?partner=12192</url><image>http://artwork-cdn.7static.com/static/img/artistimages/00/018/901/0001890195_150.jpg</image><isPlaceholderImage>true</isPlaceholderImage></artist><url>http://xw.7digital.com/artist/hit-tunes-karaoke/release/karaoke-superhits-vol-432-karaoke-version/?partner=12192</url><image>http://artwork-cdn.7static.com/static/img/sleeveart/00/036/058/0003605857_50.jpg</image><releaseDate>2014-06-19T00:00:00Z</releaseDate><formats availableDrmFree="true"><format id="17"><fileFormat>MP3</fileFormat><bitRate>320</bitRate><drmFree>true</drmFree></format><format id="33"><fileFormat>M4A</fileFormat><bitRate>320</bitRate><drmFree>true</drmFree></format></formats><label id="14988"><name>iMusician Digital</name></label><licensor id="68"><name>Kontor</name></licensor><popularity>0</popularity></release><url>http://xw.7digital.com/artist/hit-tunes-karaoke/release/karaoke-superhits-vol-432-karaoke-version/?partner=12192&amp;h=07</url><price><currency code="USD">$</currency><value>0.99</value><formattedPrice>$0.99</formattedPrice><rrp>0.99</rrp><formattedRrp>$0.99</formattedRrp><onSale>false</onSale></price><streamingReleaseDate>2014-06-19T00:00:00Z</streamingReleaseDate><discNumber>1</discNumber><popularity>0.1</popularity><number>7</number><download><releaseDate>2014-06-19T00:00:00Z</releaseDate><packages><package id="2"><description>Standard</description><price><currencyCode>USD</currencyCode><sevendigitalPrice>0.99</sevendigitalPrice><recommendedRetailPrice>0.99</recommendedRetailPrice></price><formats><format id="33"><description>AAC 320</description></format><format id="17"><description>MP3 320</description></format></formats></package></packages></download></track></searchResult><searchResult><type>track</type><score>0.24577765</score><track id="40548016"><title>The Stranger</title><version /><artist id="481860"><name>The Karaoke Channel</name><appearsAs>The Karaoke Channel</appearsAs><url>http://xw.7digital.com/artist/the-karaoke-channel/?partner=12192</url><image>http://artwork-cdn.7static.com/static/img/artistimages/00/004/818/0000481860_150.jpg</image><isPlaceholderImage>true</isPlaceholderImage></artist><trackNumber>2</trackNumber><duration>330</duration><explicitContent>false</explicitContent><isrc>USK4W0713389</isrc><type>audio</type><release id="3906467"><title>The Karaoke Channel - Sing the Stranger Like Billy Joel</title><version /><type>Album</type><artist id="481860"><name>The Karaoke Channel</name><appearsAs>The Karaoke Channel</appearsAs><url>http://xw.7digital.com/artist/the-karaoke-channel/?partner=12192</url><image>http://artwork-cdn.7static.com/static/img/artistimages/00/004/818/0000481860_150.jpg</image><isPlaceholderImage>true</isPlaceholderImage></artist><url>http://xw.7digital.com/artist/the-karaoke-channel/release/the-karaoke-channel-sing-the-stranger-like-billy-joel/?partner=12192</url><image>http://artwork-cdn.7static.com/static/img/sleeveart/00/039/064/0003906467_50.jpg</image><releaseDate>2014-10-24T03:00:00Z</releaseDate><formats availableDrmFree="true"><format id="17"><fileFormat>MP3</fileFormat><bitRate>320</bitRate><drmFree>true</drmFree></format></formats><label id="306353"><name>2014 Stingray Music Group</name></label><licensor id="21"><name>Orchard</name></licensor><popularity>0</popularity></release><url>http://xw.7digital.com/artist/the-karaoke-channel/release/the-karaoke-channel-sing-the-stranger-like-billy-joel/?partner=12192&amp;h=02</url><price><currency code="USD">$</currency><value xsi:nil="true" /><formattedPrice>N/A</formattedPrice><rrp xsi:nil="true" /><formattedRrp>N/A</formattedRrp><onSale>false</onSale></price><streamingReleaseDate>2014-10-24T00:00:00Z</streamingReleaseDate><discNumber>1</discNumber><popularity>0.1</popularity><number>2</number><download><releaseDate>2014-10-24T03:00:00Z</releaseDate><packages><package id="2"><description>Standard</description><price><currencyCode>USD</currencyCode><sevendigitalPrice xsi:nil="true" /><recommendedRetailPrice xsi:nil="true" /></price><formats><format id="17"><description>MP3 320</description></format></formats></package></packages></download></track></searchResult><searchResult><type>track</type><score>0.24464916</score><track id="35436331"><title>The Stranger</title><version>Originally Performed by Billy Joel</version><artist id="541029"><name>MIDIFine Systems</name><appearsAs>MIDIFine Systems</appearsAs><url>http://xw.7digital.com/artist/midifine-systems/?partner=12192</url><image>http://artwork-cdn.7static.com/static/img/artistimages/00/005/410/0000541029_150.jpg</image><isPlaceholderImage>true</isPlaceholderImage></artist><trackNumber>18</trackNumber><duration>332</duration><explicitContent>false</explicitContent><isrc>DESN31314512</isrc><type>audio</type><release id="3350187"><title>Best of Billy Joel Vol. 01</title><version /><type>Album</type><artist id="541029"><name>MIDIFine Systems</name><appearsAs>MIDIFine Systems</appearsAs><url>http://xw.7digital.com/artist/midifine-systems/?partner=12192</url><image>http://artwork-cdn.7static.com/static/img/artistimages/00/005/410/0000541029_150.jpg</image><isPlaceholderImage>true</isPlaceholderImage></artist><url>http://xw.7digital.com/artist/midifine-systems/release/best-of-billy-joel-vol-01/?partner=12192</url><image>http://artwork-cdn.7static.com/static/img/sleeveart/00/033/501/0003350187_50.jpg</image><releaseDate>2011-10-07T00:00:00Z</releaseDate><formats availableDrmFree="true"><format id="17"><fileFormat>MP3</fileFormat><bitRate>320</bitRate><drmFree>true</drmFree></format><format id="33"><fileFormat>M4A</fileFormat><bitRate>320</bitRate><drmFree>true</drmFree></format></formats><label id="46665"><name>Midifine Systems</name></label><licensor id="343"><name>IIP-DDS</name></licensor><popularity>0</popularity></release><url>http://xw.7digital.com/artist/midifine-systems/release/best-of-billy-joel-vol-01/?partner=12192&amp;h=18</url><price><currency code="USD">$</currency><value xsi:nil="true" /><formattedPrice>N/A</formattedPrice><rrp xsi:nil="true" /><formattedRrp>N/A</formattedRrp><onSale>false</onSale></price><streamingReleaseDate>2011-10-07T00:00:00Z</streamingReleaseDate><discNumber>1</discNumber><popularity>0.1</popularity><number>18</number><download><releaseDate>2011-10-07T00:00:00Z</releaseDate><packages><package id="2"><description>Standard</description><price><currencyCode>USD</currencyCode><sevendigitalPrice xsi:nil="true" /><recommendedRetailPrice xsi:nil="true" /></price><formats><format id="17"><description>MP3 320</description></format><format id="33"><description>AAC 320</description></format></formats></package></packages></download></track></searchResult><searchResult><type>track</type><score>0.24121898</score><track id="35637753"><title>The Stranger (Instrumental)</title><version /><artist id="15624"><name>The Professionals</name><appearsAs>The Professionals</appearsAs><url>http://xw.7digital.com/artist/the-professionals/?partner=12192</url><image>http://artwork-cdn.7static.com/static/img/artistimages/00/000/156/0000015624_150.jpg</image><isPlaceholderImage>true</isPlaceholderImage></artist><trackNumber>28</trackNumber><duration>259</duration><explicitContent>false</explicitContent><isrc>QMDA71479316</isrc><type>audio</type><release id="3376991"><title>Backing Track Database - The Professionals Perform the Hits of Billy Joel (Instrumental)</title><version /><type>Album</type><artist id="15624"><name>The Professionals</name><appearsAs>The Professionals</appearsAs><url>http://xw.7digital.com/artist/the-professionals/?partner=12192</url><image>http://artwork-cdn.7static.com/static/img/artistimages/00/000/156/0000015624_150.jpg</image><isPlaceholderImage>true</isPlaceholderImage></artist><url>http://xw.7digital.com/artist/the-professionals/release/backing-track-database-the-professionals-perform-the-hits-of-billy-joel-instrumental/?partner=12192</url><image>http://artwork-cdn.7static.com/static/img/sleeveart/00/033/769/0003376991_50.jpg</image><releaseDate>2014-03-10T03:00:00Z</releaseDate><formats availableDrmFree="true"><format id="17"><fileFormat>MP3</fileFormat><bitRate>320</bitRate><drmFree>true</drmFree></format></formats><label id="283222"><name>Suburban Squire</name></label><licensor id="21"><name>Orchard</name></licensor><popularity>0</popularity></release><url>http://xw.7digital.com/artist/the-professionals/release/backing-track-database-the-professionals-perform-the-hits-of-billy-joel-instrumental/?partner=12192&amp;h=28</url><price><currency code="USD">$</currency><value xsi:nil="true" /><formattedPrice>N/A</formattedPrice><rrp xsi:nil="true" /><formattedRrp>N/A</formattedRrp><onSale>false</onSale></price><streamingReleaseDate>2014-03-10T00:00:00Z</streamingReleaseDate><discNumber>1</discNumber><popularity>0.1</popularity><number>28</number><download><releaseDate>2014-03-10T03:00:00Z</releaseDate><packages><package id="2"><description>Standard</description><price><currencyCode>USD</currencyCode><sevendigitalPrice xsi:nil="true" /><recommendedRetailPrice xsi:nil="true" /></price><formats><format id="17"><description>MP3 320</description></format></formats></package></packages></download></track></searchResult><searchResult><type>track</type><score>0.23553182</score><track id="35367728"><title>The Stranger</title><version>Originally Performed by Billy Joel</version><artist id="541029"><name>MIDIFine Systems</name><appearsAs>MIDIFine Systems</appearsAs><url>http://xw.7digital.com/artist/midifine-systems/?partner=12192</url><image>http://artwork-cdn.7static.com/static/img/artistimages/00/005/410/0000541029_150.jpg</image><isPlaceholderImage>true</isPlaceholderImage></artist><trackNumber>8</trackNumber><duration>332</duration><explicitContent>false</explicitContent><isrc>DESN31301799</isrc><type>audio</type><release id="3347994"><title>Best for Musicians No. 104</title><version /><type>Album</type><artist id="541029"><name>MIDIFine Systems</name><appearsAs>MIDIFine Systems</appearsAs><url>http://xw.7digital.com/artist/midifine-systems/?partner=12192</url><image>http://artwork-cdn.7static.com/static/img/artistimages/00/005/410/0000541029_150.jpg</image><isPlaceholderImage>true</isPlaceholderImage></artist><url>http://xw.7digital.com/artist/midifine-systems/release/best-for-musicians-no-104/?partner=12192</url><image>http://artwork-cdn.7static.com/static/img/sleeveart/00/033/479/0003347994_50.jpg</image><releaseDate>2010-02-06T00:00:00Z</releaseDate><formats availableDrmFree="true"><format id="17"><fileFormat>MP3</fileFormat><bitRate>320</bitRate><drmFree>true</drmFree></format><format id="33"><fileFormat>M4A</fileFormat><bitRate>320</bitRate><drmFree>true</drmFree></format></formats><label id="46665"><name>Midifine Systems</name></label><licensor id="343"><name>IIP-DDS</name></licensor><popularity>0</popularity></release><url>http://xw.7digital.com/artist/midifine-systems/release/best-for-musicians-no-104/?partner=12192&amp;h=08</url><price><currency code="USD">$</currency><value xsi:nil="true" /><formattedPrice>N/A</formattedPrice><rrp xsi:nil="true" /><formattedRrp>N/A</formattedRrp><onSale>false</onSale></price><streamingReleaseDate>2010-02-06T00:00:00Z</streamingReleaseDate><discNumber>1</discNumber><popularity>0.1</popularity><number>8</number><download><releaseDate>2010-02-06T00:00:00Z</releaseDate><packages><package id="2"><description>Standard</description><price><currencyCode>USD</currencyCode><sevendigitalPrice xsi:nil="true" /><recommendedRetailPrice xsi:nil="true" /></price><formats><format id="17"><description>MP3 320</description></format><format id="33"><description>AAC 320</description></format></formats></package></packages></download></track></searchResult><searchResult><type>track</type><score>0.23477203</score><track id="12482128"><title>The Stranger</title><version /><artist id="455792"><name>The Wanted</name><appearsAs>The Wanted</appearsAs><url>http://xw.7digital.com/artist/the-wanted/?partner=12192</url><image>http://artwork-cdn.7static.com/static/img/artistimages/00/004/557/0000455792_150.jpg</image><isPlaceholderImage>true</isPlaceholderImage></artist><trackNumber>5</trackNumber><duration>292</duration><explicitContent>false</explicitContent><isrc>GBQRF0835785</isrc><type>audio</type><release id="1129174"><title>A Tribute to Billy Joel</title><version /><type>Album</type><artist id="455792"><name>The Wanted</name><appearsAs>The Wanted</appearsAs><url>http://xw.7digital.com/artist/the-wanted/?partner=12192</url><image>http://artwork-cdn.7static.com/static/img/artistimages/00/004/557/0000455792_150.jpg</image><isPlaceholderImage>true</isPlaceholderImage></artist><url>http://xw.7digital.com/artist/the-wanted/release/tribute-to-billy-joel/?partner=12192</url><image>http://artwork-cdn.7static.com/static/img/sleeveart/00/011/291/0001129174_50.jpg</image><releaseDate>2009-08-17T03:00:00Z</releaseDate><formats availableDrmFree="true"><format id="17"><fileFormat>MP3</fileFormat><bitRate>320</bitRate><drmFree>true</drmFree></format></formats><label id="10787"><name>Vanilla OMP</name></label><licensor id="21"><name>Orchard</name></licensor><popularity>0</popularity></release><url>http://xw.7digital.com/artist/the-wanted/release/tribute-to-billy-joel/?partner=12192&amp;h=05</url><price><currency code="USD">$</currency><value xsi:nil="true" /><formattedPrice>N/A</formattedPrice><rrp xsi:nil="true" /><formattedRrp>N/A</formattedRrp><onSale>false</onSale></price><streamingReleaseDate>2009-08-17T00:00:00Z</streamingReleaseDate><discNumber>1</discNumber><popularity>0.1</popularity><number>5</number><download><releaseDate>2009-08-17T03:00:00Z</releaseDate><packages><package id="2"><description>Standard</description><price><currencyCode>USD</currencyCode><sevendigitalPrice xsi:nil="true" /><recommendedRetailPrice xsi:nil="true" /></price><formats><format id="17"><description>MP3 320</description></format></formats></package></packages></download></track></searchResult></searchResults></response>