<?xml version="1.0" encoding="utf-8"?><response status="ok" version="1.2" xsi:noNamespaceSchemaLocation="http://api.7digital.com/1.2/static/7digitalAPI.xsd" xmlns:xsd="http://www.w3.org/2001/XMLSchema" xmlns:xsi="http://www.w3.org/2001/XMLSchema-instance"><searchResults><page>1</page><pageSize>10</pageSize><totalItems>2</totalItems><searchResult><type>track</type><score>0.21482612</score><track id="12531210"><title>Belong  </title><version>Original</version><artist id="924103"><name>Dharmaone, Tuomo</name><appearsAs>Dharmaone, Tuomo</appearsAs><url>http://xw.7digital.com/artist/dharmaone-tuomo/?partner=12192</url><image>http://artwork-cdn.7static.com/static/img/artistimages/00/009/241/0000924103_150.jpg</image><isPlaceholderImage>true</isPlaceholderImage></artist><trackNumber>9</trackNumber><duration>479</duration><explicitContent>false</explicitContent><isrc>FIN250200013</isrc><type>audio</type><release id="1132877"><title>Liquid Assets</title><version /><type>Album</type><artist id="209"><name>Various Artists</name><appearsAs>Various Artists</appearsAs><url>http://xw.7digital.com/artist/various-artists/?partner=12192</url><image>http://artwork-cdn.7static.com/static/img/artistimages/00/000/002/0000000209_150.jpg</image><isPlaceholderImage>true</isPlaceholderImage></artist><url>http://xw.7digital.com/artist/various-artists/release/liquid-assets-1132877/?partner=12192</url><image>http://artwork-cdn.7static.com/static/img/sleeveart/00/011/328/0001132877_50.jpg</image><releaseDate>2009-11-30T00:00:00Z</releaseDate><formats availableDrmFree="true"><format id="17"><fileFormat>MP3</fileFormat><bitRate>320</bitRate><drmFree>true</drmFree></format><format id="33"><fileFormat>M4A</fileFormat><bitRate>320</bitRate><drmFree>true</drmFree></format></formats><label id="72033"><name>Nine2Five</name></label><licensor id="319"><name>Paradise Entertainment &amp; Distribution</name></licensor><popularity>0</popularity></release><url>http://xw.7digital.com/artist/various-artists/release/liquid-assets-1132877/?partner=12192&amp;h=09</url><price><currency code="USD">$</currency><value>0.99</value><formattedPrice>$0.99</formattedPrice><rrp>0.99</rrp><formattedRrp>$0.99</formattedRrp><onSale>false</onSale></price><streamingReleaseDate>2009-11-30T00:00:00Z</streamingReleaseDate><discNumber>1</discNumber><popularity>0.1</popularity><number>9</number><download><releaseDate>2009-11-30T00:00:00Z</releaseDate><packages><package id="2"><description>Standard</description><price><currencyCode>USD</currencyCode><sevendigitalPrice>0.99</sevendigitalPrice><recommendedRetailPrice>0.99</recommendedRetailPrice></price><formats><format id="33"><description>AAC 320</description></format><format id="17"><description>MP3 320</description></format></formats></package></packages></download></track></searchResult><searchResult><type>track</type><score>0.21482612</score><track id="22323311"><title>Belong</title><version>Jimpster House Mix</version><artist id="1463640"><name>Dharmaone</name><appearsAs>Dharmaone</appearsAs><url>http://xw.7digital.com/artist/dharmaone/?partner=12192</url><image>http://artwork-cdn.7static.com/static/img/artistimages/00/014/636/0001463640_150.jpg</image><isPlaceholderImage>true</isPlaceholderImage></artist><trackNumber>6</trackNumber><duration>445</duration><explicitContent>false</explicitContent><isrc>DEY470701778</isrc><type>audio</type><release id="2067570"><title>Deepest Shades Of House Vol. 4</title><version /><type>Album</type><artist id="209"><name>Various Artists</name><appearsAs>Various Artists</appearsAs><url>http://xw.7digital.com/artist/various-artists/?partner=12192</url><image>http://artwork-cdn.7static.com/static/img/artistimages/00/000/002/0000000209_150.jpg</image><isPlaceholderImage>true</isPlaceholderImage></artist><url>http://xw.7digital.com/artist/various-artists/release/deepest-shades-of-house-vol-4/?partner=12192</url><image>http://artwork-cdn.7static.com/static/img/sleeveart/00/020/675/0002067570_50.jpg</image><releaseDate>2007-07-13T00:00:00Z</releaseDate><formats availableDrmFree="true"><format id="17"><fileFormat>MP3</fileFormat><bitRate>320</bitRate><drmFree>true</drmFree></format><format id="33"><fileFormat>M4A</fileFormat><bitRate>320</bitRate><drmFree>true</drmFree></format></formats><label id="70650"><name>Laka-Tosh</name></label><licensor id="319"><name>Paradise Entertainment &amp; Distribution</name></licensor><popularity>0</popularity></release><url>http://xw.7digital.com/artist/various-artists/release/deepest-shades-of-house-vol-4/?partner=12192&amp;h=06</url><price><currency code="USD">$</currency><value>0.99</value><formattedPrice>$0.99</formattedPrice><rrp>0.99</rrp><formattedRrp>$0.99</formattedRrp><onSale>false</onSale></price><streamingReleaseDate>2007-07-13T00:00:00Z</streamingReleaseDate><discNumber>1</discNumber><popularity>0.1</popularity><number>6</number><download><releaseDate>2007-07-13T00:00:00Z</releaseDate><packages><package id="2"><description>Standard</description><price><currencyCode>USD</currencyCode><sevendigitalPrice>0.99</sevendigitalPrice><recommendedRetailPrice>0.99</recommendedRetailPrice></price><formats><format id="33"><description>AAC 320</description></format><format id="17"><description>MP3 320</description></format></formats></package></packages></download></track></searchResult></searchResults></response>