<?xml version="1.0" encoding="utf-8"?><response status="ok" version="1.2" xsi:noNamespaceSchemaLocation="http://api.7digital.com/1.2/static/7digitalAPI.xsd" xmlns:xsd="http://www.w3.org/2001/XMLSchema" xmlns:xsi="http://www.w3.org/2001/XMLSchema-instance"><searchResults><page>1</page><pageSize>10</pageSize><totalItems>216</totalItems><searchResult><type>track</type><score>0.430264</score><track id="56061722"><title>The Stars Down to Earth (To a Passerby)</title><version /><artist id="3379800"><name>Ghost Valley Choir</name><appearsAs>Ghost Valley Choir</appearsAs><url>http://xw.7digital.com/artist/ghost-valley-choir/?partner=12192</url><image>http://artwork-cdn.7static.com/static/img/artistimages/00/033/798/0003379800_150.jpg</image><isPlaceholderImage>true</isPlaceholderImage></artist><trackNumber>7</trackNumber><duration>285</duration><explicitContent>false</explicitContent><isrc>FR59R1617120</isrc><type>audio</type><release id="5573230"><title>Keep Holding the Light, Disgraced Fox</title><version /><type>Album</type><artist id="3379800"><name>Ghost Valley Choir</name><appearsAs>Ghost Valley Choir</appearsAs><url>http://xw.7digital.com/artist/ghost-valley-choir/?partner=12192</url><image>http://artwork-cdn.7static.com/static/img/artistimages/00/033/798/0003379800_150.jpg</image><isPlaceholderImage>true</isPlaceholderImage></artist><url>http://xw.7digital.com/artist/ghost-valley-choir/release/keep-holding-the-light-disgraced-fox-5573230/?partner=12192</url><image>http://artwork-cdn.7static.com/static/img/sleeveart/00/055/732/0005573230_50.jpg</image><releaseDate>2016-07-06T03:00:00Z</releaseDate><formats availableDrmFree="true"><format id="17"><fileFormat>MP3</fileFormat><bitRate>320</bitRate><drmFree>true</drmFree></format><format id="33"><fileFormat>M4A</fileFormat><bitRate>320</bitRate><drmFree>true</drmFree></format></formats><label id="609632"><name>Ghost Valley Choir</name></label><licensor id="166"><name>Believe</name></licensor><popularity>0</popularity></release><url>http://xw.7digital.com/artist/ghost-valley-choir/release/keep-holding-the-light-disgraced-fox-5573230/?partner=12192&amp;h=07</url><price><currency code="USD">$</currency><value xsi:nil="true" /><formattedPrice>N/A</formattedPrice><rrp xsi:nil="true" /><formattedRrp>N/A</formattedRrp><onSale>false</onSale></price><streamingReleaseDate>2016-07-06T03:00:00Z</streamingReleaseDate><discNumber>1</discNumber><popularity>0.26</popularity><number>7</number><download><releaseDate>2016-07-06T03:00:00Z</releaseDate><packages><package id="2"><description>Standard</description><price><currencyCode>USD</currencyCode><sevendigitalPrice xsi:nil="true" /><recommendedRetailPrice xsi:nil="true" /></price><formats><format id="33"><description>AAC 320</description></format><format id="17"><description>MP3 320</description></format></formats></package></packages></download></track></searchResult><searchResult><type>track</type><score>0.40222993</score><track id="57320628"><title>You Will Never Grow Old / That's an Irish Lullaby / When I Grow Too Old to Dream / Down in the Valley / If Those Lips Could Only Speak</title><version /><artist id="986319"><name>John McSweeney</name><appearsAs>John McSweeney</appearsAs><url>http://xw.7digital.com/artist/john-mcsweeney/?partner=12192</url><image>http://artwork-cdn.7static.com/static/img/artistimages/00/009/863/0000986319_150.jpg</image><isPlaceholderImage>true</isPlaceholderImage></artist><trackNumber>3</trackNumber><duration>338</duration><explicitContent>false</explicitContent><isrc>GBKPL1670426</isrc><type>audio</type><release id="5712389"><title>Songs You Know by Heart, Vol. 1</title><version /><type>Album</type><artist id="986319"><name>John McSweeney</name><appearsAs>John McSweeney</appearsAs><url>http://xw.7digital.com/artist/john-mcsweeney/?partner=12192</url><image>http://artwork-cdn.7static.com/static/img/artistimages/00/009/863/0000986319_150.jpg</image><isPlaceholderImage>true</isPlaceholderImage></artist><url>http://xw.7digital.com/artist/john-mcsweeney/release/songs-you-know-by-heart-vol-1-5712389/?partner=12192</url><image>http://artwork-cdn.7static.com/static/img/sleeveart/00/057/123/0005712389_50.jpg</image><releaseDate>2016-08-26T03:00:00Z</releaseDate><formats availableDrmFree="true"><format id="17"><fileFormat>MP3</fileFormat><bitRate>320</bitRate><drmFree>true</drmFree></format><format id="33"><fileFormat>M4A</fileFormat><bitRate>320</bitRate><drmFree>true</drmFree></format></formats><label id="540784"><name>Checked Label Services</name></label><licensor id="235"><name>AWAL</name></licensor><popularity>0</popularity></release><url>http://xw.7digital.com/artist/john-mcsweeney/release/songs-you-know-by-heart-vol-1-5712389/?partner=12192&amp;h=03</url><price><currency code="USD">$</currency><value xsi:nil="true" /><formattedPrice>N/A</formattedPrice><rrp xsi:nil="true" /><formattedRrp>N/A</formattedRrp><onSale>false</onSale></price><streamingReleaseDate>2016-08-26T03:00:00Z</streamingReleaseDate><discNumber>1</discNumber><popularity>0.27</popularity><number>3</number><download><releaseDate>2016-08-26T03:00:00Z</releaseDate><packages><package id="2"><description>Standard</description><price><currencyCode>USD</currencyCode><sevendigitalPrice xsi:nil="true" /><recommendedRetailPrice xsi:nil="true" /></price><formats><format id="33"><description>AAC 320</description></format><format id="17"><description>MP3 320</description></format></formats></package></packages></download></track></searchResult><searchResult><type>track</type><score>0.40025625</score><track id="57044209"><title>Down in the Valley to Pray</title><version>Instrumental</version><artist id="2206851"><name>Jeff Victor</name><appearsAs>Jeff Victor</appearsAs><url>http://xw.7digital.com/artist/jeff-victor/?partner=12192</url><image>http://artwork-cdn.7static.com/static/img/artistimages/00/022/068/0002206851_150.jpg</image><isPlaceholderImage>true</isPlaceholderImage></artist><trackNumber>18</trackNumber><duration>126</duration><explicitContent>false</explicitContent><isrc>USP3J0801533</isrc><type>audio</type><release id="5677805"><title>Amazing Grace</title><version /><type>Album</type><artist id="3428515"><name>Jeff Victor &amp; Rebecca Arons</name><appearsAs>Jeff Victor &amp; Rebecca Arons</appearsAs><url>http://xw.7digital.com/artist/jeff-victor-and-rebecca-arons/?partner=12192</url><image>http://artwork-cdn.7static.com/static/img/artistimages/00/034/285/0003428515_150.jpg</image><isPlaceholderImage>true</isPlaceholderImage></artist><url>http://xw.7digital.com/artist/jeff-victor-and-rebecca-arons/release/amazing-grace-5677805/?partner=12192</url><image>http://artwork-cdn.7static.com/static/img/sleeveart/00/056/778/0005677805_50.jpg</image><releaseDate>2016-01-01T03:00:00Z</releaseDate><formats availableDrmFree="true"><format id="17"><fileFormat>MP3</fileFormat><bitRate>320</bitRate><drmFree>true</drmFree></format><format id="33"><fileFormat>M4A</fileFormat><bitRate>320</bitRate><drmFree>true</drmFree></format></formats><label id="331831"><name>Lifescapes</name></label><licensor id="21"><name>Orchard</name></licensor><popularity>0</popularity></release><url>http://xw.7digital.com/artist/jeff-victor-and-rebecca-arons/release/amazing-grace-5677805/?partner=12192&amp;h=18</url><price><currency code="USD">$</currency><value xsi:nil="true" /><formattedPrice>N/A</formattedPrice><rrp xsi:nil="true" /><formattedRrp>N/A</formattedRrp><onSale>false</onSale></price><streamingReleaseDate>2016-01-01T00:00:00Z</streamingReleaseDate><discNumber>1</discNumber><popularity>0.27</popularity><number>18</number><download><releaseDate>2016-01-01T03:00:00Z</releaseDate><packages><package id="2"><description>Standard</description><price><currencyCode>USD</currencyCode><sevendigitalPrice xsi:nil="true" /><recommendedRetailPrice xsi:nil="true" /></price><formats><format id="33"><description>AAC 320</description></format><format id="17"><description>MP3 320</description></format></formats></package></packages></download></track></searchResult><searchResult><type>track</type><score>0.3921354</score><track id="56523307"><title>Down to the Valley</title><version /><artist id="824448"><name>Herman Frank</name><appearsAs>Herman Frank</appearsAs><url>http://xw.7digital.com/artist/herman-frank/?partner=12192</url><image>http://artwork-cdn.7static.com/static/img/artistimages/00/008/244/0000824448_150.jpg</image><isPlaceholderImage>true</isPlaceholderImage></artist><trackNumber>7</trackNumber><duration>247</duration><explicitContent>false</explicitContent><isrc>DEU601606409</isrc><type>audio</type><release id="5621422"><title>Loyal to None</title><version>Bonus Version</version><type>Album</type><artist id="824448"><name>Herman Frank</name><appearsAs>Herman Frank</appearsAs><url>http://xw.7digital.com/artist/herman-frank/?partner=12192</url><image>http://artwork-cdn.7static.com/static/img/artistimages/00/008/244/0000824448_150.jpg</image><isPlaceholderImage>true</isPlaceholderImage></artist><url>http://xw.7digital.com/artist/herman-frank/release/loyal-to-none-bonus-version-5621422/?partner=12192</url><image>http://artwork-cdn.7static.com/static/img/sleeveart/00/056/214/0005621422_50.jpg</image><releaseDate>2016-09-09T03:00:00Z</releaseDate><formats availableDrmFree="true"><format id="17"><fileFormat>MP3</fileFormat><bitRate>320</bitRate><drmFree>true</drmFree></format><format id="33"><fileFormat>M4A</fileFormat><bitRate>320</bitRate><drmFree>true</drmFree></format></formats><label id="38218"><name>AFM Records</name></label><licensor id="166"><name>Believe</name></licensor><popularity>0</popularity></release><url>http://xw.7digital.com/artist/herman-frank/release/loyal-to-none-bonus-version-5621422/?partner=12192&amp;h=07</url><price><currency code="USD">$</currency><value xsi:nil="true" /><formattedPrice>N/A</formattedPrice><rrp xsi:nil="true" /><formattedRrp>N/A</formattedRrp><onSale>false</onSale></price><streamingReleaseDate>2016-09-09T03:00:00Z</streamingReleaseDate><discNumber>1</discNumber><popularity>0.26</popularity><number>7</number><download><releaseDate>2016-09-09T03:00:00Z</releaseDate><packages><package id="2"><description>Standard</description><price><currencyCode>USD</currencyCode><sevendigitalPrice xsi:nil="true" /><recommendedRetailPrice xsi:nil="true" /></price><formats><format id="33"><description>AAC 320</description></format><format id="17"><description>MP3 320</description></format></formats></package></packages></download></track></searchResult><searchResult><type>track</type><score>0.3893351</score><track id="56799863"><title>Down in the Valley</title><version /><artist id="19910"><name>Pete Seeger</name><appearsAs>Pete Seeger</appearsAs><url>http://xw.7digital.com/artist/pete-seeger/?partner=12192</url><image>http://artwork-cdn.7static.com/static/img/artistimages/00/000/199/0000019910_150.jpg</image><isPlaceholderImage>true</isPlaceholderImage></artist><trackNumber>3</trackNumber><duration>219</duration><explicitContent>false</explicitContent><isrc>DEL111601131</isrc><type>audio</type><release id="5651985"><title>Musical Moments to Remember: Pete Seeger (Remastered 2016)</title><version /><type>Album</type><artist id="19910"><name>Pete Seeger</name><appearsAs>Pete Seeger</appearsAs><url>http://xw.7digital.com/artist/pete-seeger/?partner=12192</url><image>http://artwork-cdn.7static.com/static/img/artistimages/00/000/199/0000019910_150.jpg</image><isPlaceholderImage>true</isPlaceholderImage></artist><url>http://xw.7digital.com/artist/pete-seeger/release/musical-moments-to-remember-pete-seeger-remastered-2016-5651985/?partner=12192</url><image>http://artwork-cdn.7static.com/static/img/sleeveart/00/056/519/0005651985_50.jpg</image><releaseDate>2016-08-26T03:00:00Z</releaseDate><formats availableDrmFree="true"><format id="17"><fileFormat>MP3</fileFormat><bitRate>320</bitRate><drmFree>true</drmFree></format><format id="33"><fileFormat>M4A</fileFormat><bitRate>320</bitRate><drmFree>true</drmFree></format></formats><label id="524168"><name>Jube Legends</name></label><licensor id="334"><name>Naxos of America Inc.</name></licensor><popularity>0</popularity></release><url>http://xw.7digital.com/artist/pete-seeger/release/musical-moments-to-remember-pete-seeger-remastered-2016-5651985/?partner=12192&amp;h=03</url><price><currency code="USD">$</currency><value xsi:nil="true" /><formattedPrice>N/A</formattedPrice><rrp xsi:nil="true" /><formattedRrp>N/A</formattedRrp><onSale>false</onSale></price><streamingReleaseDate>2016-08-26T00:00:00Z</streamingReleaseDate><discNumber>1</discNumber><popularity>0.31</popularity><number>3</number><download><releaseDate>2016-08-26T03:00:00Z</releaseDate><packages><package id="2"><description>Standard</description><price><currencyCode>USD</currencyCode><sevendigitalPrice xsi:nil="true" /><recommendedRetailPrice xsi:nil="true" /></price><formats><format id="33"><description>AAC 320</description></format><format id="17"><description>MP3 320</description></format></formats></package></packages></download></track></searchResult><searchResult><type>track</type><score>0.32575765</score><track id="31159441"><title>Down To The Valley</title><version /><artist id="374690"><name>Patchworks</name><appearsAs>Patchworks</appearsAs><url>http://xw.7digital.com/artist/patchworks/?partner=12192</url><image>http://artwork-cdn.7static.com/static/img/artistimages/00/003/746/0000374690_150.jpg</image><isPlaceholderImage>true</isPlaceholderImage></artist><trackNumber>2</trackNumber><duration>292</duration><explicitContent>false</explicitContent><isrc>USBPD0500002</isrc><type>audio</type><release id="2919468"><title>Sugar E.P.</title><version /><type>Single</type><artist id="374690"><name>Patchworks</name><appearsAs>Patchworks</appearsAs><url>http://xw.7digital.com/artist/patchworks/?partner=12192</url><image>http://artwork-cdn.7static.com/static/img/artistimages/00/003/746/0000374690_150.jpg</image><isPlaceholderImage>true</isPlaceholderImage></artist><url>http://xw.7digital.com/artist/patchworks/release/sugar-e-p/?partner=12192</url><image>http://artwork-cdn.7static.com/static/img/sleeveart/00/029/194/0002919468_50.jpg</image><releaseDate>2004-01-03T00:00:00Z</releaseDate><formats availableDrmFree="true"><format id="17"><fileFormat>MP3</fileFormat><bitRate>320</bitRate><drmFree>true</drmFree></format><format id="33"><fileFormat>M4A</fileFormat><bitRate>320</bitRate><drmFree>true</drmFree></format></formats><label id="17453"><name>Still Music</name></label><licensor id="366"><name>Above Board Distribution Limited</name></licensor><popularity>0</popularity></release><url>http://xw.7digital.com/artist/patchworks/release/sugar-e-p/?partner=12192&amp;h=02</url><price><currency code="USD">$</currency><value>0.99</value><formattedPrice>$0.99</formattedPrice><rrp>0.99</rrp><formattedRrp>$0.99</formattedRrp><onSale>false</onSale></price><streamingReleaseDate>2004-01-03T00:00:00Z</streamingReleaseDate><discNumber>1</discNumber><popularity>0.1</popularity><number>2</number><download><releaseDate>2004-01-03T00:00:00Z</releaseDate><packages><package id="2"><description>Standard</description><price><currencyCode>USD</currencyCode><sevendigitalPrice>0.99</sevendigitalPrice><recommendedRetailPrice>0.99</recommendedRetailPrice></price><formats><format id="17"><description>MP3 320</description></format><format id="33"><description>AAC 320</description></format></formats></package></packages></download></track></searchResult><searchResult><type>track</type><score>0.32575765</score><track id="33603727"><title>Down To The Valley</title><version /><artist id="374690"><name>Patchworks</name><appearsAs>Patchworks</appearsAs><url>http://xw.7digital.com/artist/patchworks/?partner=12192</url><image>http://artwork-cdn.7static.com/static/img/artistimages/00/003/746/0000374690_150.jpg</image><isPlaceholderImage>true</isPlaceholderImage></artist><trackNumber>5</trackNumber><duration>303</duration><explicitContent>false</explicitContent><isrc>DEZ651327918</isrc><type>audio</type><release id="3160077"><title>Early Recordings</title><version /><type>Album</type><artist id="374690"><name>Patchworks</name><appearsAs>Patchworks</appearsAs><url>http://xw.7digital.com/artist/patchworks/?partner=12192</url><image>http://artwork-cdn.7static.com/static/img/artistimages/00/003/746/0000374690_150.jpg</image><isPlaceholderImage>true</isPlaceholderImage></artist><url>http://xw.7digital.com/artist/patchworks/release/early-recordings/?partner=12192</url><image>http://artwork-cdn.7static.com/static/img/sleeveart/00/031/600/0003160077_50.jpg</image><releaseDate>2014-01-10T00:00:00Z</releaseDate><formats availableDrmFree="true"><format id="17"><fileFormat>MP3</fileFormat><bitRate>320</bitRate><drmFree>true</drmFree></format><format id="33"><fileFormat>M4A</fileFormat><bitRate>320</bitRate><drmFree>true</drmFree></format></formats><label id="17856"><name>Patchworks Productions</name></label><licensor id="47"><name>Finetunes</name></licensor><popularity>0</popularity></release><url>http://xw.7digital.com/artist/patchworks/release/early-recordings/?partner=12192&amp;h=05</url><price><currency code="USD">$</currency><value>0.99</value><formattedPrice>$0.99</formattedPrice><rrp>0.99</rrp><formattedRrp>$0.99</formattedRrp><onSale>false</onSale></price><discNumber>1</discNumber><popularity>0.1</popularity><number>5</number><download><releaseDate>2014-01-10T00:00:00Z</releaseDate><packages><package id="2"><description>Standard</description><price><currencyCode>USD</currencyCode><sevendigitalPrice>0.99</sevendigitalPrice><recommendedRetailPrice>0.99</recommendedRetailPrice></price><formats><format id="17"><description>MP3 320</description></format><format id="33"><description>AAC 320</description></format></formats></package></packages></download></track></searchResult><searchResult><type>track</type><score>0.23279707</score><track id="37591432"><title>The Good Old Way (Down in the Valley to Pray)</title><version>Original</version><artist id="2188998"><name>Sparky &amp; Rhonda Rucker</name><appearsAs>Sparky &amp; Rhonda Rucker</appearsAs><url>http://xw.7digital.com/artist/sparky-and-rhonda-rucker-1/?partner=12192</url><image>http://artwork-cdn.7static.com/static/img/artistimages/00/021/889/0002188998_150.jpg</image><isPlaceholderImage>true</isPlaceholderImage></artist><trackNumber>6</trackNumber><duration>172</duration><explicitContent>false</explicitContent><isrc>ushm21441013</isrc><type>audio</type><release id="3578951"><title>The Mountains Above and the Valleys Below</title><version /><type>Album</type><artist id="2188998"><name>Sparky &amp; Rhonda Rucker</name><appearsAs>Sparky &amp; Rhonda Rucker</appearsAs><url>http://xw.7digital.com/artist/sparky-and-rhonda-rucker-1/?partner=12192</url><image>http://artwork-cdn.7static.com/static/img/artistimages/00/021/889/0002188998_150.jpg</image><isPlaceholderImage>true</isPlaceholderImage></artist><url>http://xw.7digital.com/artist/sparky-and-rhonda-rucker-1/release/the-mountains-above-and-the-valleys-below/?partner=12192</url><image>http://artwork-cdn.7static.com/static/img/sleeveart/00/035/789/0003578951_50.jpg</image><releaseDate>2008-01-04T00:00:00Z</releaseDate><formats availableDrmFree="true"><format id="17"><fileFormat>MP3</fileFormat><bitRate>320</bitRate><drmFree>true</drmFree></format><format id="33"><fileFormat>M4A</fileFormat><bitRate>320</bitRate><drmFree>true</drmFree></format></formats><label id="302391"><name>Tremont Productions</name></label><licensor id="310"><name>CD Baby</name></licensor><popularity>0</popularity></release><url>http://xw.7digital.com/artist/sparky-and-rhonda-rucker-1/release/the-mountains-above-and-the-valleys-below/?partner=12192&amp;h=06</url><price><currency code="USD">$</currency><value>0.99</value><formattedPrice>$0.99</formattedPrice><rrp>0.99</rrp><formattedRrp>$0.99</formattedRrp><onSale>false</onSale></price><discNumber>1</discNumber><popularity>0.1</popularity><number>6</number><download><releaseDate>2008-01-04T00:00:00Z</releaseDate><packages><package id="2"><description>Standard</description><price><currencyCode>USD</currencyCode><sevendigitalPrice>0.99</sevendigitalPrice><recommendedRetailPrice>0.99</recommendedRetailPrice></price><formats><format id="17"><description>MP3 320</description></format><format id="33"><description>AAC 320</description></format></formats></package></packages></download></track></searchResult><searchResult><type>track</type><score>0.2300742</score><track id="46702286"><title>When the Moon Goes Down in the Valley to Pray</title><version /><artist id="2806223"><name>Male Groups</name><appearsAs>Male Groups</appearsAs><url>http://xw.7digital.com/artist/male-groups/?partner=12192</url><image>http://artwork-cdn.7static.com/static/img/artistimages/00/028/062/0002806223_150.jpg</image><isPlaceholderImage>true</isPlaceholderImage></artist><trackNumber>8</trackNumber><duration>156</duration><explicitContent>false</explicitContent><isrc>GBPS81524654</isrc><type>audio</type><release id="4581480"><title>Something on My Mind</title><version /><type>Album</type><artist id="2806223"><name>Male Groups</name><appearsAs>Male Groups</appearsAs><url>http://xw.7digital.com/artist/male-groups/?partner=12192</url><image>http://artwork-cdn.7static.com/static/img/artistimages/00/028/062/0002806223_150.jpg</image><isPlaceholderImage>true</isPlaceholderImage></artist><url>http://xw.7digital.com/artist/male-groups/release/something-on-my-mind/?partner=12192</url><image>http://artwork-cdn.7static.com/static/img/sleeveart/00/045/814/0004581480_50.jpg</image><releaseDate>2015-06-04T03:00:00Z</releaseDate><formats availableDrmFree="true"><format id="17"><fileFormat>MP3</fileFormat><bitRate>320</bitRate><drmFree>true</drmFree></format><format id="33"><fileFormat>M4A</fileFormat><bitRate>320</bitRate><drmFree>true</drmFree></format></formats><label id="320734"><name>Suncoast Music</name></label><licensor id="21"><name>Orchard</name></licensor><popularity>0</popularity></release><url>http://xw.7digital.com/artist/male-groups/release/something-on-my-mind/?partner=12192&amp;h=08</url><price><currency code="USD">$</currency><value xsi:nil="true" /><formattedPrice>N/A</formattedPrice><rrp xsi:nil="true" /><formattedRrp>N/A</formattedRrp><onSale>false</onSale></price><streamingReleaseDate>2015-06-04T00:00:00Z</streamingReleaseDate><discNumber>1</discNumber><popularity>0.1</popularity><number>8</number><download><releaseDate>2015-06-04T03:00:00Z</releaseDate><packages><package id="2"><description>Standard</description><price><currencyCode>USD</currencyCode><sevendigitalPrice xsi:nil="true" /><recommendedRetailPrice xsi:nil="true" /></price><formats><format id="17"><description>MP3 320</description></format><format id="33"><description>AAC 320</description></format></formats></package></packages></download></track></searchResult><searchResult><type>track</type><score>0.2300742</score><track id="37314858"><title>Down to the Valley to Pray</title><version>Original</version><artist id="1940074"><name>Mark Geslison &amp; Geoff Groberg</name><appearsAs>Mark Geslison &amp; Geoff Groberg</appearsAs><url>http://xw.7digital.com/artist/mark-geslison-and-geoff-groberg/?partner=12192</url><image>http://artwork-cdn.7static.com/static/img/artistimages/00/019/400/0001940074_150.jpg</image><isPlaceholderImage>true</isPlaceholderImage></artist><trackNumber>5</trackNumber><duration>160</duration><explicitContent>false</explicitContent><isrc>ushm21417315</isrc><type>audio</type><release id="3549706"><title>All Things Bright and Beautiful</title><version /><type>Album</type><artist id="1940074"><name>Mark Geslison &amp; Geoff Groberg</name><appearsAs>Mark Geslison &amp; Geoff Groberg</appearsAs><url>http://xw.7digital.com/artist/mark-geslison-and-geoff-groberg/?partner=12192</url><image>http://artwork-cdn.7static.com/static/img/artistimages/00/019/400/0001940074_150.jpg</image><isPlaceholderImage>true</isPlaceholderImage></artist><url>http://xw.7digital.com/artist/mark-geslison-and-geoff-groberg/release/all-things-bright-and-beautiful/?partner=12192</url><image>http://artwork-cdn.7static.com/static/img/sleeveart/00/035/497/0003549706_50.jpg</image><releaseDate>2014-05-19T00:00:00Z</releaseDate><formats availableDrmFree="true"><format id="17"><fileFormat>MP3</fileFormat><bitRate>320</bitRate><drmFree>true</drmFree></format><format id="33"><fileFormat>M4A</fileFormat><bitRate>320</bitRate><drmFree>true</drmFree></format></formats><label id="332455"><name>Geslison Groberg, LLC</name></label><licensor id="310"><name>CD Baby</name></licensor><popularity>0</popularity></release><url>http://xw.7digital.com/artist/mark-geslison-and-geoff-groberg/release/all-things-bright-and-beautiful/?partner=12192&amp;h=05</url><price><currency code="USD">$</currency><value>0.99</value><formattedPrice>$0.99</formattedPrice><rrp>0.99</rrp><formattedRrp>$0.99</formattedRrp><onSale>false</onSale></price><discNumber>1</discNumber><popularity>0.1</popularity><number>5</number><download><releaseDate>2014-05-19T00:00:00Z</releaseDate><packages><package id="2"><description>Standard</description><price><currencyCode>USD</currencyCode><sevendigitalPrice>0.99</sevendigitalPrice><recommendedRetailPrice>0.99</recommendedRetailPrice></price><formats><format id="17"><description>MP3 320</description></format><format id="33"><description>AAC 320</description></format></formats></package></packages></download></track></searchResult></searchResults></response>