<?xml version="1.0" encoding="utf-8"?><response status="ok" version="1.2" xsi:noNamespaceSchemaLocation="http://api.7digital.com/1.2/static/7digitalAPI.xsd" xmlns:xsd="http://www.w3.org/2001/XMLSchema" xmlns:xsi="http://www.w3.org/2001/XMLSchema-instance"><searchResults><page>1</page><pageSize>10</pageSize><totalItems>40</totalItems><searchResult><type>track</type><score>0.45461884</score><track id="12727412"><title>What Else Is There To Do</title><version /><artist id="15256"><name>Lil Wayne</name><appearsAs>Lil Wayne</appearsAs><url>http://xw.7digital.com/artist/lil-wayne-(2)/?partner=12192</url><image>http://artwork-cdn.7static.com/static/img/artistimages/00/000/152/0000015256_150.jpg</image><isPlaceholderImage>true</isPlaceholderImage></artist><trackNumber>3</trackNumber><duration>62</duration><explicitContent>false</explicitContent><isrc>US38L0804210</isrc><type>audio</type><release id="1150626"><title>Dedication 3 Gangsta Grillz</title><version /><type>Album</type><artist id="934880"><name>Lil Wayne &amp; DJ Drama</name><appearsAs>Lil Wayne &amp; DJ Drama</appearsAs><url>http://xw.7digital.com/artist/lil-wayne-and-dj-drama/?partner=12192</url><image>http://artwork-cdn.7static.com/static/img/artistimages/00/009/348/0000934880_150.jpg</image><isPlaceholderImage>true</isPlaceholderImage></artist><url>http://xw.7digital.com/artist/lil-wayne-and-dj-drama/release/dedication-3-gangsta-grillz/?partner=12192</url><image>http://artwork-cdn.7static.com/static/img/sleeveart/00/011/506/0001150626_50.jpg</image><releaseDate>2008-04-01T00:00:00Z</releaseDate><formats availableDrmFree="true"><format id="17"><fileFormat>MP3</fileFormat><bitRate>320</bitRate><drmFree>true</drmFree></format><format id="33"><fileFormat>M4A</fileFormat><bitRate>320</bitRate><drmFree>true</drmFree></format></formats><label id="73258"><name>Big Kanaka - SoSouth</name></label><licensor id="238"><name>INgrooves</name></licensor><popularity>0</popularity></release><url>http://xw.7digital.com/artist/lil-wayne-and-dj-drama/release/dedication-3-gangsta-grillz/?partner=12192&amp;h=03</url><price><currency code="USD">$</currency><value>0.99</value><formattedPrice>$0.99</formattedPrice><rrp>0.99</rrp><formattedRrp>$0.99</formattedRrp><onSale>false</onSale></price><streamingReleaseDate>2008-04-01T00:00:00Z</streamingReleaseDate><discNumber>1</discNumber><popularity>0.36</popularity><number>3</number><download><releaseDate>2008-04-01T00:00:00Z</releaseDate><packages><package id="2"><description>Standard</description><price><currencyCode>USD</currencyCode><sevendigitalPrice>0.99</sevendigitalPrice><recommendedRetailPrice>0.99</recommendedRetailPrice></price><formats><format id="33"><description>AAC 320</description></format><format id="17"><description>MP3 320</description></format></formats></package></packages></download></track></searchResult><searchResult><type>track</type><score>0.32683536</score><track id="57434603"><title>What Else Is There to Do?</title><version /><artist id="3448226"><name>Kyle Dixon</name><appearsAs>Kyle Dixon</appearsAs><url>http://xw.7digital.com/artist/kyle-dixon/?partner=12192</url><image>http://artwork-cdn.7static.com/static/img/artistimages/00/034/482/0003448226_150.jpg</image><isPlaceholderImage>true</isPlaceholderImage></artist><trackNumber>35</trackNumber><duration>119</duration><explicitContent>false</explicitContent><isrc>USLS51683435</isrc><type>audio</type><release id="5722807"><title>Stranger Things, Vol. 1 (A Netflix Original Series Soundtrack)</title><version /><type>Album</type><artist id="3448225"><name>Kyle Dixon &amp; Michael Stein</name><appearsAs>Kyle Dixon &amp; Michael Stein</appearsAs><url>http://xw.7digital.com/artist/kyle-dixon-and-michael-stein/?partner=12192</url><image>http://artwork-cdn.7static.com/static/img/artistimages/00/034/482/0003448225_150.jpg</image><isPlaceholderImage>true</isPlaceholderImage></artist><url>http://xw.7digital.com/artist/kyle-dixon-and-michael-stein/release/stranger-things-vol-1-a-netflix-original-series-soundtrack-5722807/?partner=12192</url><image>http://artwork-cdn.7static.com/static/img/sleeveart/00/057/228/0005722807_50.jpg</image><releaseDate>2016-08-12T03:00:00Z</releaseDate><formats availableDrmFree="true"><format id="17"><fileFormat>MP3</fileFormat><bitRate>320</bitRate><drmFree>true</drmFree></format><format id="33"><fileFormat>M4A</fileFormat><bitRate>320</bitRate><drmFree>true</drmFree></format></formats><label id="73002"><name>Lakeshore Records</name></label><licensor id="21"><name>Orchard</name></licensor><popularity>0</popularity></release><url>http://xw.7digital.com/artist/kyle-dixon-and-michael-stein/release/stranger-things-vol-1-a-netflix-original-series-soundtrack-5722807/?partner=12192&amp;h=35</url><price><currency code="USD">$</currency><value xsi:nil="true" /><formattedPrice>N/A</formattedPrice><rrp xsi:nil="true" /><formattedRrp>N/A</formattedRrp><onSale>false</onSale></price><streamingReleaseDate>2016-08-12T00:00:00Z</streamingReleaseDate><discNumber>1</discNumber><popularity>0.26</popularity><number>35</number><download><releaseDate>2016-08-12T03:00:00Z</releaseDate><packages><package id="2"><description>Standard</description><price><currencyCode>USD</currencyCode><sevendigitalPrice xsi:nil="true" /><recommendedRetailPrice xsi:nil="true" /></price><formats><format id="33"><description>AAC 320</description></format><format id="17"><description>MP3 320</description></format></formats></package></packages></download></track></searchResult><searchResult><type>track</type><score>0.32683536</score><track id="56371400"><title>What Else Is There</title><version>Original Mix</version><artist id="3396329"><name>Max Olsen feat. Tinaya</name><appearsAs>Max Olsen feat. Tinaya</appearsAs><url>http://xw.7digital.com/artist/max-olsen-feat-tinaya/?partner=12192</url><image>http://artwork-cdn.7static.com/static/img/artistimages/00/033/963/0003396329_150.jpg</image><isPlaceholderImage>true</isPlaceholderImage></artist><trackNumber>2</trackNumber><duration>311</duration><explicitContent>false</explicitContent><isrc>CA9DI1600029</isrc><type>audio</type><release id="5607128"><title>Ibiza 2016</title><version /><type>Album</type><artist id="209"><name>Various Artists</name><appearsAs>Various Artists</appearsAs><url>http://xw.7digital.com/artist/various-artists/?partner=12192</url><image>http://artwork-cdn.7static.com/static/img/artistimages/00/000/002/0000000209_150.jpg</image><isPlaceholderImage>true</isPlaceholderImage></artist><url>http://xw.7digital.com/artist/various-artists/release/ibiza-2016-5607128/?partner=12192</url><image>http://artwork-cdn.7static.com/static/img/sleeveart/00/056/071/0005607128_50.jpg</image><releaseDate>2016-08-05T03:00:00Z</releaseDate><formats availableDrmFree="true"><format id="17"><fileFormat>MP3</fileFormat><bitRate>320</bitRate><drmFree>true</drmFree></format><format id="33"><fileFormat>M4A</fileFormat><bitRate>320</bitRate><drmFree>true</drmFree></format></formats><label id="150811"><name>Jungle Funk Recordings</name></label><licensor id="223"><name>Label Worx Limited</name></licensor><popularity>0</popularity></release><url>http://xw.7digital.com/artist/various-artists/release/ibiza-2016-5607128/?partner=12192&amp;h=02</url><price><currency code="USD">$</currency><value>0.99</value><formattedPrice>$0.99</formattedPrice><rrp>0.99</rrp><formattedRrp>$0.99</formattedRrp><onSale>false</onSale></price><streamingReleaseDate>2016-08-05T03:00:00Z</streamingReleaseDate><discNumber>1</discNumber><popularity>0.26</popularity><number>2</number><download><releaseDate>2016-08-05T03:00:00Z</releaseDate><packages><package id="2"><description>Standard</description><price><currencyCode>USD</currencyCode><sevendigitalPrice>0.99</sevendigitalPrice><recommendedRetailPrice>0.99</recommendedRetailPrice></price><formats><format id="33"><description>AAC 320</description></format><format id="17"><description>MP3 320</description></format></formats></package></packages></download></track></searchResult><searchResult><type>track</type><score>0.32683536</score><track id="55840664"><title>What Else Is There to Say?</title><version /><artist id="3252093"><name>Brusque Twins</name><appearsAs>Brusque Twins</appearsAs><url>http://xw.7digital.com/artist/brusque-twins/?partner=12192</url><image>http://artwork-cdn.7static.com/static/img/artistimages/00/032/520/0003252093_150.jpg</image><isPlaceholderImage>true</isPlaceholderImage></artist><trackNumber>3</trackNumber><duration>333</duration><explicitContent>false</explicitContent><isrc>CAXS11200003</isrc><type>audio</type><release id="5547284"><title>A Voice in the Night</title><version /><type>Album</type><artist id="3252093"><name>Brusque Twins</name><appearsAs>Brusque Twins</appearsAs><url>http://xw.7digital.com/artist/brusque-twins/?partner=12192</url><image>http://artwork-cdn.7static.com/static/img/artistimages/00/032/520/0003252093_150.jpg</image><isPlaceholderImage>true</isPlaceholderImage></artist><url>http://xw.7digital.com/artist/brusque-twins/release/a-voice-in-the-night-5547284/?partner=12192</url><image>http://artwork-cdn.7static.com/static/img/sleeveart/00/055/472/0005547284_50.jpg</image><releaseDate>2016-04-15T03:00:00Z</releaseDate><formats availableDrmFree="true"><format id="17"><fileFormat>MP3</fileFormat><bitRate>320</bitRate><drmFree>true</drmFree></format><format id="33"><fileFormat>M4A</fileFormat><bitRate>320</bitRate><drmFree>true</drmFree></format></formats><label id="345028"><name>Visage Musique</name></label><licensor id="166"><name>Believe</name></licensor><popularity>0</popularity></release><url>http://xw.7digital.com/artist/brusque-twins/release/a-voice-in-the-night-5547284/?partner=12192&amp;h=03</url><price><currency code="USD">$</currency><value xsi:nil="true" /><formattedPrice>N/A</formattedPrice><rrp xsi:nil="true" /><formattedRrp>N/A</formattedRrp><onSale>false</onSale></price><streamingReleaseDate>2016-04-15T03:00:00Z</streamingReleaseDate><discNumber>1</discNumber><popularity>0.26</popularity><number>3</number><download><releaseDate>2016-04-15T03:00:00Z</releaseDate><packages><package id="2"><description>Standard</description><price><currencyCode>USD</currencyCode><sevendigitalPrice xsi:nil="true" /><recommendedRetailPrice xsi:nil="true" /></price><formats><format id="33"><description>AAC 320</description></format><format id="17"><description>MP3 320</description></format></formats></package></packages></download></track></searchResult><searchResult><type>track</type><score>0.27538982</score><track id="6239235"><title>What else is there</title><version /><artist id="10543"><name>Röyksopp</name><appearsAs>Royksopp</appearsAs><url>http://xw.7digital.com/artist/röyksopp/?partner=12192</url><image>http://artwork-cdn.7static.com/static/img/artistimages/00/000/105/0000010543_150.jpg</image><isPlaceholderImage>true</isPlaceholderImage></artist><trackNumber>17</trackNumber><duration>396</duration><explicitContent>false</explicitContent><isrc>FRS940500063</isrc><type>audio</type><release id="563676"><title>Hotel Dubai Deluxe - By Lisa Loud</title><version /><type>Album</type><artist id="209"><name>Various Artists</name><appearsAs>Various Artists</appearsAs><url>http://xw.7digital.com/artist/various-artists/?partner=12192</url><image>http://artwork-cdn.7static.com/static/img/artistimages/00/000/002/0000000209_150.jpg</image><isPlaceholderImage>true</isPlaceholderImage></artist><url>http://xw.7digital.com/artist/various-artists/release/hotel-dubai-deluxe-by-lisa-loud-1/?partner=12192</url><image>http://artwork-cdn.7static.com/static/img/sleeveart/00/005/636/0000563676_50.jpg</image><releaseDate>2009-01-06T02:00:00Z</releaseDate><formats availableDrmFree="true"><format id="17"><fileFormat>MP3</fileFormat><bitRate>320</bitRate><drmFree>true</drmFree></format><format id="33"><fileFormat>M4A</fileFormat><bitRate>320</bitRate><drmFree>true</drmFree></format></formats><label id="7381"><name>Crazy Diamond Recordings</name></label><licensor id="21"><name>Orchard</name></licensor><popularity>0</popularity></release><url>http://xw.7digital.com/artist/various-artists/release/hotel-dubai-deluxe-by-lisa-loud-1/?partner=12192&amp;h=17</url><price><currency code="USD">$</currency><value xsi:nil="true" /><formattedPrice>N/A</formattedPrice><rrp xsi:nil="true" /><formattedRrp>N/A</formattedRrp><onSale>false</onSale></price><streamingReleaseDate>2009-01-06T00:00:00Z</streamingReleaseDate><discNumber>1</discNumber><popularity>0.1</popularity><number>17</number><download><releaseDate>2009-01-06T02:00:00Z</releaseDate><packages><package id="2"><description>Standard</description><price><currencyCode>USD</currencyCode><sevendigitalPrice xsi:nil="true" /><recommendedRetailPrice xsi:nil="true" /></price><formats><format id="17"><description>MP3 320</description></format><format id="33"><description>AAC 320</description></format></formats></package></packages></download></track></searchResult><searchResult><type>track</type><score>0.22031187</score><track id="30088930"><title>What Else Is There? (Hamman Mix)</title><version /><artist id="537901"><name>Mustapha Mali</name><appearsAs>Mustapha Mali</appearsAs><url>http://xw.7digital.com/artist/mustapha-mali/?partner=12192</url><image>http://artwork-cdn.7static.com/static/img/artistimages/00/005/379/0000537901_150.jpg</image><isPlaceholderImage>true</isPlaceholderImage></artist><trackNumber>30</trackNumber><duration>226</duration><explicitContent>false</explicitContent><isrc>GBKEZ1000034</isrc><type>audio</type><release id="2810252"><title>Arabic Chillout Lounge</title><version /><type>Album</type><artist id="209"><name>Various Artists</name><appearsAs>Various Artists</appearsAs><url>http://xw.7digital.com/artist/various-artists/?partner=12192</url><image>http://artwork-cdn.7static.com/static/img/artistimages/00/000/002/0000000209_150.jpg</image><isPlaceholderImage>true</isPlaceholderImage></artist><url>http://xw.7digital.com/artist/various-artists/release/arabic-chillout-lounge/?partner=12192</url><image>http://artwork-cdn.7static.com/static/img/sleeveart/00/028/102/0002810252_50.jpg</image><releaseDate>2012-02-15T03:00:00Z</releaseDate><formats availableDrmFree="true"><format id="17"><fileFormat>MP3</fileFormat><bitRate>320</bitRate><drmFree>true</drmFree></format></formats><label id="206586"><name>The Ganesha</name></label><licensor id="21"><name>Orchard</name></licensor><popularity>0</popularity></release><url>http://xw.7digital.com/artist/various-artists/release/arabic-chillout-lounge/?partner=12192&amp;h=30</url><price><currency code="USD">$</currency><value xsi:nil="true" /><formattedPrice>N/A</formattedPrice><rrp xsi:nil="true" /><formattedRrp>N/A</formattedRrp><onSale>false</onSale></price><streamingReleaseDate>2012-02-15T00:00:00Z</streamingReleaseDate><discNumber>1</discNumber><popularity>0.1</popularity><number>30</number><download><releaseDate>2012-02-15T03:00:00Z</releaseDate><packages><package id="2"><description>Standard</description><price><currencyCode>USD</currencyCode><sevendigitalPrice xsi:nil="true" /><recommendedRetailPrice xsi:nil="true" /></price><formats><format id="17"><description>MP3 320</description></format></formats></package></packages></download></track></searchResult><searchResult><type>track</type><score>0.1762495</score><track id="10779809"><title>What Else Is There</title><version /><artist id="815504"><name>Daphna Sadeh And The Voyagers</name><appearsAs>Daphna Sadeh And The Voyagers</appearsAs><url>http://xw.7digital.com/artist/daphna-sadeh-and-the-voyagers/?partner=12192</url><image>http://artwork-cdn.7static.com/static/img/artistimages/00/008/155/0000815504_150.jpg</image><isPlaceholderImage>true</isPlaceholderImage></artist><trackNumber>4</trackNumber><duration>301</duration><explicitContent>false</explicitContent><isrc>USCRW0913404</isrc><type>audio</type><release id="981342"><title>Reconciliation</title><version /><type>Album</type><artist id="815504"><name>Daphna Sadeh And The Voyagers</name><appearsAs>Daphna Sadeh And The Voyagers</appearsAs><url>http://xw.7digital.com/artist/daphna-sadeh-and-the-voyagers/?partner=12192</url><image>http://artwork-cdn.7static.com/static/img/artistimages/00/008/155/0000815504_150.jpg</image><isPlaceholderImage>true</isPlaceholderImage></artist><url>http://xw.7digital.com/artist/daphna-sadeh-and-the-voyagers/release/reconciliation-981342/?partner=12192</url><image>http://artwork-cdn.7static.com/static/img/sleeveart/00/009/813/0000981342_50.jpg</image><releaseDate>2009-02-24T02:00:00Z</releaseDate><formats availableDrmFree="true"><format id="17"><fileFormat>MP3</fileFormat><bitRate>320</bitRate><drmFree>true</drmFree></format><format id="33"><fileFormat>M4A</fileFormat><bitRate>320</bitRate><drmFree>true</drmFree></format></formats><label id="50668"><name>Tzadik</name></label><licensor id="282"><name>E1 Entertainment</name></licensor><popularity>0</popularity></release><url>http://xw.7digital.com/artist/daphna-sadeh-and-the-voyagers/release/reconciliation-981342/?partner=12192&amp;h=04</url><price><currency code="USD">$</currency><value>0.99</value><formattedPrice>$0.99</formattedPrice><rrp>0.99</rrp><formattedRrp>$0.99</formattedRrp><onSale>false</onSale></price><discNumber>1</discNumber><popularity>0.1</popularity><number>4</number><download><releaseDate>2009-02-24T02:00:00Z</releaseDate><packages><package id="2"><description>Standard</description><price><currencyCode>USD</currencyCode><sevendigitalPrice>0.99</sevendigitalPrice><recommendedRetailPrice>0.99</recommendedRetailPrice></price><formats><format id="33"><description>AAC 320</description></format><format id="17"><description>MP3 320</description></format></formats></package></packages></download></track></searchResult><searchResult><type>track</type><score>0.1762495</score><track id="12728614"><title>What Else Is There To Do [Screwed]</title><version /><artist id="15256"><name>Lil Wayne</name><appearsAs>Lil Wayne</appearsAs><url>http://xw.7digital.com/artist/lil-wayne-(2)/?partner=12192</url><image>http://artwork-cdn.7static.com/static/img/artistimages/00/000/152/0000015256_150.jpg</image><isPlaceholderImage>true</isPlaceholderImage></artist><trackNumber>3</trackNumber><duration>78</duration><explicitContent>false</explicitContent><isrc>US38L1000672</isrc><type>audio</type><release id="1150792"><title>[Screwed] Dedication 3 Gangsta Grillz</title><version /><type>Album</type><artist id="934880"><name>Lil Wayne &amp; DJ Drama</name><appearsAs>Lil Wayne &amp; DJ Drama</appearsAs><url>http://xw.7digital.com/artist/lil-wayne-and-dj-drama/?partner=12192</url><image>http://artwork-cdn.7static.com/static/img/artistimages/00/009/348/0000934880_150.jpg</image><isPlaceholderImage>true</isPlaceholderImage></artist><url>http://xw.7digital.com/artist/lil-wayne-and-dj-drama/release/screwed-dedication-3-gangsta-grillz/?partner=12192</url><image>http://artwork-cdn.7static.com/static/img/sleeveart/00/011/507/0001150792_50.jpg</image><releaseDate>2008-06-01T00:00:00Z</releaseDate><formats availableDrmFree="true"><format id="17"><fileFormat>MP3</fileFormat><bitRate>320</bitRate><drmFree>true</drmFree></format><format id="33"><fileFormat>M4A</fileFormat><bitRate>320</bitRate><drmFree>true</drmFree></format></formats><label id="73258"><name>Big Kanaka - SoSouth</name></label><licensor id="238"><name>INgrooves</name></licensor><popularity>0</popularity></release><url>http://xw.7digital.com/artist/lil-wayne-and-dj-drama/release/screwed-dedication-3-gangsta-grillz/?partner=12192&amp;h=03</url><price><currency code="USD">$</currency><value>0.99</value><formattedPrice>$0.99</formattedPrice><rrp>0.99</rrp><formattedRrp>$0.99</formattedRrp><onSale>false</onSale></price><streamingReleaseDate>2008-06-01T00:00:00Z</streamingReleaseDate><discNumber>1</discNumber><popularity>0.1</popularity><number>3</number><download><releaseDate>2008-06-01T00:00:00Z</releaseDate><packages><package id="2"><description>Standard</description><price><currencyCode>USD</currencyCode><sevendigitalPrice>0.99</sevendigitalPrice><recommendedRetailPrice>0.99</recommendedRetailPrice></price><formats><format id="33"><description>AAC 320</description></format><format id="17"><description>MP3 320</description></format></formats></package></packages></download></track></searchResult><searchResult><type>track</type><score>0.1762495</score><track id="10006158"><title>What Else Is There</title><version /><artist id="738406"><name>Disposed to Mirth</name><appearsAs>Disposed to Mirth</appearsAs><url>http://xw.7digital.com/artist/disposed-to-mirth/?partner=12192</url><image>http://artwork-cdn.7static.com/static/img/artistimages/00/007/384/0000738406_150.jpg</image><isPlaceholderImage>true</isPlaceholderImage></artist><trackNumber>7</trackNumber><duration>239</duration><explicitContent>false</explicitContent><isrc>DEKL51004237</isrc><type>audio</type><release id="909667"><title>Menschenhai</title><version /><type>Album</type><artist id="738406"><name>Disposed to Mirth</name><appearsAs>Disposed to Mirth</appearsAs><url>http://xw.7digital.com/artist/disposed-to-mirth/?partner=12192</url><image>http://artwork-cdn.7static.com/static/img/artistimages/00/007/384/0000738406_150.jpg</image><isPlaceholderImage>true</isPlaceholderImage></artist><url>http://xw.7digital.com/artist/disposed-to-mirth/release/menschenhai/?partner=12192</url><image>http://artwork-cdn.7static.com/static/img/sleeveart/00/009/096/0000909667_50.jpg</image><releaseDate>2010-07-23T00:00:00Z</releaseDate><formats availableDrmFree="true"><format id="17"><fileFormat>MP3</fileFormat><bitRate>320</bitRate><drmFree>true</drmFree></format><format id="33"><fileFormat>M4A</fileFormat><bitRate>320</bitRate><drmFree>true</drmFree></format></formats><label id="58425"><name>NOIZGATE Records</name></label><licensor id="47"><name>Finetunes</name></licensor><popularity>0</popularity></release><url>http://xw.7digital.com/artist/disposed-to-mirth/release/menschenhai/?partner=12192&amp;h=07</url><price><currency code="USD">$</currency><value>0.99</value><formattedPrice>$0.99</formattedPrice><rrp>0.99</rrp><formattedRrp>$0.99</formattedRrp><onSale>false</onSale></price><discNumber>1</discNumber><popularity>0.1</popularity><number>7</number><download><releaseDate>2010-07-23T00:00:00Z</releaseDate><packages><package id="2"><description>Standard</description><price><currencyCode>USD</currencyCode><sevendigitalPrice>0.99</sevendigitalPrice><recommendedRetailPrice>0.99</recommendedRetailPrice></price><formats><format id="33"><description>AAC 320</description></format><format id="17"><description>MP3 320</description></format></formats></package></packages></download></track></searchResult><searchResult><type>track</type><score>0.1762495</score><track id="30006586"><title>What Else Is There</title><version>Original</version><artist id="1916951"><name>Onemillionsteps</name><appearsAs>Onemillionsteps</appearsAs><url>http://xw.7digital.com/artist/onemillionsteps/?partner=12192</url><image>http://artwork-cdn.7static.com/static/img/artistimages/00/019/169/0001916951_150.jpg</image><isPlaceholderImage>true</isPlaceholderImage></artist><trackNumber>6</trackNumber><duration>318</duration><explicitContent>false</explicitContent><isrc>uscgj1321438</isrc><type>audio</type><release id="2800879"><title>Onemillionsteps EP</title><version /><type>Album</type><artist id="1916951"><name>Onemillionsteps</name><appearsAs>Onemillionsteps</appearsAs><url>http://xw.7digital.com/artist/onemillionsteps/?partner=12192</url><image>http://artwork-cdn.7static.com/static/img/artistimages/00/019/169/0001916951_150.jpg</image><isPlaceholderImage>true</isPlaceholderImage></artist><url>http://xw.7digital.com/artist/onemillionsteps/release/onemillionsteps-ep/?partner=12192</url><image>http://artwork-cdn.7static.com/static/img/sleeveart/00/028/008/0002800879_50.jpg</image><releaseDate>2013-03-22T00:00:00Z</releaseDate><formats availableDrmFree="true"><format id="17"><fileFormat>MP3</fileFormat><bitRate>320</bitRate><drmFree>true</drmFree></format><format id="33"><fileFormat>M4A</fileFormat><bitRate>320</bitRate><drmFree>true</drmFree></format></formats><label id="204639"><name>Onemillionsteps</name></label><licensor id="310"><name>CD Baby</name></licensor><popularity>0</popularity></release><url>http://xw.7digital.com/artist/onemillionsteps/release/onemillionsteps-ep/?partner=12192&amp;h=06</url><price><currency code="USD">$</currency><value>0.99</value><formattedPrice>$0.99</formattedPrice><rrp>0.99</rrp><formattedRrp>$0.99</formattedRrp><onSale>false</onSale></price><streamingReleaseDate>2013-03-22T00:00:00Z</streamingReleaseDate><discNumber>1</discNumber><popularity>0.1</popularity><number>6</number><download><releaseDate>2013-03-22T00:00:00Z</releaseDate><packages><package id="2"><description>Standard</description><price><currencyCode>USD</currencyCode><sevendigitalPrice>0.99</sevendigitalPrice><recommendedRetailPrice>0.99</recommendedRetailPrice></price><formats><format id="17"><description>MP3 320</description></format><format id="33"><description>AAC 320</description></format></formats></package></packages></download></track></searchResult></searchResults></response>